{
  "user": [
    {
      "id": 1,
      "email": "nghiahoang@gmail.com",
      "username": "nghiahoang",
      "password": "123456",
      "createdAt": 12012021,
      "updatedAt": 12022021
    },
    {
      "id": 2,
      "email": "hieuHoang@gmail.com",
      "username": "hieuhoang",
      "password": "123456",
      "createdAt": 12012021,
      "updatedAt": 12022021
    },
    {
      "id": 3,
      "email": "duchoang@gmail.com",
      "username": "duchoang",
      "password": "123456",
      "createdAt": 12012021,
      "updatedAt": 12022021
    },
    {
      "id": 4,
      "email": "huongle@gmail.com",
      "username": "huongle",
      "password": "123456",
      "createdAt": 12012021,
      "updatedAt": 12022021
    }
  ],
  "categories": [
    {
      "id": 1,
      "name": "ao jacket",
      "createdAt": 12012021,
      "updatedAt": 12022021
    }
  ],
  "products": [
    {
      "name": "Jacket man 1",
      "description": "Some quick example text to build on the card title and make up the bulk of the card's content. hello ",
      "salePrice": "90000",
      "image": "https://i.pinimg.com/564x/55/10/26/551026569bf22cc8cf6862c6041f0d79.jpg",
      "isActive": true,
      "stock": "111",
      "id": 1
    },
    {
      "name": "Jacket man 1",
      "description": "Some quick example text to build on the card title and make up the bulk of the card's content. hello ",
      "salePrice": "90000",
      "image": "https://i.pinimg.com/564x/84/48/af/8448af80944eaca909874361f6009221.jpg",
      "isActive": true,
      "stock": "111",
      "id": 2
    },
    {
      "name": "vest",
      "description": "Hello Some quick example text to build on the card title and make up the bulk of the card's content.",
      "salePrice": "222222",
      "image": "https://encrypted-tbn0.gstatic.com/images?q=tbn:ANd9GcQBAzhfeGhwloV0f72W6A3yW6PbWep_OrsKKdQrZ1rd0bKTNkJLLBCwlhxLrUNPl7MfpfE&usqp=CAU",
      "isActive": "yes",
      "stock": "100",
      "id": 3
    },
    {
      "name": "T-shirt",
      "description": "Hello Some quick example text to build on the card title and make up the bulk of the card's content.",
      "salePrice": "222222",
      "image": "https://encrypted-tbn0.gstatic.com/images?q=tbn:ANd9GcRTxp9n69z6OQuqSa9vqT0DlrC7A-06ttS2CA&usqp=CAU",
      "isActive": "yes",
      "stock": "100",
      "id": 4
    },
    {
      "name": "long shirt",
      "description": "Hello Some quick example text to build on the card title and make up the bulk of the card's content.",
      "salePrice": "222222",
      "image": "https://rukminim1.flixcart.com/image/332/398/kasjjww0/t-shirt/p/m/c/m-fc4175-fastcolors-original-imafsaynmfhp5gnj.jpeg?q=50",
      "isActive": "yes",
      "stock": "100",
      "id": 5
    },
    {
      "name": "T-shirt",
      "description": "Hello Some quick example text to build on the card title and make up the bulk of the card's content.",
      "salePrice": "222222",
      "image": "https://assets.myntassets.com/dpr_1.5,q_60,w_400,c_limit,fl_progressive/assets/images/productimage/2020/1/17/d71045b2-4300-4395-b110-f652fa00e9e51579211471795-1.jpg",
      "isActive": "yes",
      "stock": "100",
      "id": 6
    },
    {
      "name": "coat",
      "description": "Hello Some quick example text to build on the card title and make up the bulk of the card's content.",
      "salePrice": "222222",
      "image": "https://digitalcontent.api.tesco.com/v2/media/homepage/66c4b330-3185-4c7e-a613-561954e343ac/2132-FF-Mens-Portrait-SmallStamp-OrangeTechJacket.jpeg",
      "isActive": "yes",
      "stock": "100",
      "id": 7
    },
    {
      "name": "jacket",
      "description": "Hello Some quick example text to build on the card title and make up the bulk of the card's content.",
      "salePrice": "222222",
      "image": "https://hips.hearstapps.com/vader-prod.s3.amazonaws.com/1540487828-paige-kinley-bomber-mens-essentials-1540487806.jpg",
      "isActive": "yes",
      "stock": "100",
      "id": 8
    },
    {
      "name": "jacket man 2",
      "description": "Hello man Some quick example text to build on the card title and make up the bulk of the card's content.",
      "salePrice": "1222290",
      "image": "https://www.themodestman.com/wp-content/uploads/2021/07/Noragi-jacket-outfit-650x880.jpg",
      "isActive": "yes",
      "stock": "199",
      "id": 9
    }
  ],
  "profile": {
    "name": "typicode"
  }
}